Workbook

Sheet Cover
M10: Discounted Cash Flow Valuation
M11: The Coca-Cola Company
M12: 5-Year Forecast Model
M15: Simon Norrman
M16: 22 February 2026
M19: This model estimates the intrinsic value of The Coca-Cola Company using a 5-year DCF approach based on publicly available financial data
A34: *This model was built for educational purposes only and does not constitute investment advice

Sheet Assumptions
B2: Coca Cola DCF - Assumptions
A4: x | B4: Ticker | C4: KO
B5: Date | C5: 46076
A7: x | B7: Key Model Assumptions
A9: x | B9: Operating Assumptions
B10: Revenue Growth (Years 1-5) | E10: 0.055
B11: EBIT Margin | E11: 0.295
B12: Tax Rate | E12: 0.23
B13: Depreciation (% of Revenue) | E13: 0.025
B14: CapEx (% of Revenue) | E14: 0.04
B15: Change in NWC (% of Revenue) | E15: 0.01
A17: x | B17: WACC Assumptions
B18: Risk-Free Rate | E18: 0.04
B19: Equity Risk Premium | E19: 0.055
B20: Beta | E20: 0.6
B21: Cost of Debt | E21: 0.045
B22: Target Debt % | E22: 0.3
B23: Target Equity % | E23: 0.7
A25: x | B25: Terminal Assumptions
B26: Terminal Growth Rate | E26: 0.0275

Sheet Historical Financials
B2: Historical Financials
B4: (Figures in USD millions)
A5: x | B5: Income Statement | C5: 2021 | D5: =C5+1 -> 2022 | E5: =D5+1 -> 2023 | F5: =E5+1 -> 2024 | G5: =F5+1 -> 2025
B6: Revenue | C6: 38655 | D6: 43004 | E6: 45754 | F6: 47061 | G6: 47941
B7: % Growth | C7: xx | D7: =(D6/C6)-1 -> 0.11250808 | E7: =(E6/D6)-1 -> 0.06394754 | F7: =(F6/E6)-1 -> 0.028565808 | G7: =(G6/F6)-1 -> 0.018699135
B8: EBIT (Operating Income) | C8: 10308 | D8: 10909 | E8: 11311 | F8: 9992 | G8: 13762
B9: EBIT Margin | C9: =C8/C6 -> 0.26666667 | D9: =D8/D6 -> 0.25367408 | E9: =E8/E6 -> 0.24721336 | F9: =F8/F6 -> 0.21232018 | G9: =G8/G6 -> 0.28706118
B10: Income Before Income Taxes | C10: 12425 | D10: 11686 | E10: 12925 | F10: 13086 | G10: 15998
B11: Income Tax Expense | C11: 2621 | D11: 2115 | E11: 2249 | F11: 2437 | G11: 2861
B12: Effective Tax Rate | C12: =C11/C10 -> 0.21094567 | D12: =D11/D10 -> 0.18098579 | E12: =E11/E10 -> 0.17400387 | F12: =F11/F10 -> 0.18622956 | G12: =G11/G10 -> 0.17883485
B13: Net Income | C13: 9771 | D13: 9542 | E13: 10714 | F13: 10631 | G13: 13107
A16: x | B16: Cash Flow Items | C16: 2021 | D16: =C16+1 -> 2022 | E16: =D16+1 -> 2023 | F16: =E16+1 -> 2024 | G16: =F16+1 -> 2025
B17: Depreciation & Amorisation | C17: 1425 | D17: 1260 | E17: 1128 | F17: 1075 | G17: 1050
B18: CapEx | C18: 1367 | D18: 1484 | E18: 1852 | F18: 2064 | G18: 2112
B19: Change in Net Working Capital | C19: -1325 | D19: 605 | E19: 846 | F19: 6234 | G19: 7208
A22: x | B22: Free Cash Flow (Historical) | C22: 2021 | D22: =C22+1 -> 2022 | E22: =D22+1 -> 2023 | F22: =E22+1 -> 2024 | G22: =F22+1 -> 2025
B23: NOPAT | C23: 8134 | D23: 8935 | E23: 9343 | F23: 8131 | G23: 11301
B24: Unlevered Free Cash Flow | C24: =C23+C17-C18-C19 -> 9517 | D24: =D23+D17-D18-D19 -> 8106 | E24: =E23+E17-E18-E19 -> 7773 | F24: =F23+F17-F18-F19 -> 908 | G24: =G23+G17-G18-G19 -> 3031

Sheet Forecast
B3: Forecast Financials (2026-2030)
B5: (Figures in USD millions)
A6: x | B6: Operating Forecast | C6: 2026 | D6: =C6+1 -> 2027 | E6: =D6+1 -> 2028 | F6: =E6+1 -> 2029 | G6: =F6+1 -> 2030
B7: Revenue | C7: ='Historical Financials'!G6*(1+Assumptions!$E$10) -> 50577.755 | D7: =C7*(1+Assumptions!$E$10) -> 53359.532 | E7: =D7*(1+Assumptions!$E$10) -> 56294.306 | F7: =E7*(1+Assumptions!$E$10) -> 59390.493 | G7: =F7*(1+Assumptions!$E$10) -> 62656.97
B8: % Growth | C8: =Assumptions!$E$10 -> 0.055 | D8: =Assumptions!$E$10 -> 0.055 | E8: =Assumptions!$E$10 -> 0.055 | F8: =Assumptions!$E$10 -> 0.055 | G8: =Assumptions!$E$10 -> 0.055
B9: EBIT Margin | C9: =Assumptions!$E$11 -> 0.295 | D9: =Assumptions!$E$11 -> 0.295 | E9: =Assumptions!$E$11 -> 0.295 | F9: =Assumptions!$E$11 -> 0.295 | G9: =Assumptions!$E$11 -> 0.295
B10: EBIT | C10: =C7*C9 -> 14920.438 | D10: =D7*D9 -> 15741.062 | E10: =E7*E9 -> 16606.82 | F10: =F7*F9 -> 17520.195 | G10: =G7*G9 -> 18483.806
B11: Tax Rate | C11: =Assumptions!$E$12 -> 0.23 | D11: =Assumptions!$E$12 -> 0.23 | E11: =Assumptions!$E$12 -> 0.23 | F11: =Assumptions!$E$12 -> 0.23 | G11: =Assumptions!$E$12 -> 0.23
B12: NOPAT | C12: =C10*(1-C11) -> 11488.737 | D12: =D10*(1-D11) -> 12120.618 | E12: =E10*(1-E11) -> 12787.252 | F12: =F10*(1-F11) -> 13490.55 | G12: =G10*(1-G11) -> 14232.531
A15: x | B15: Reinvestment | C15: 2026 | D15: =C15+1 -> 2027 | E15: =D15+1 -> 2028 | F15: =E15+1 -> 2029 | G15: =F15+1 -> 2030
B16: Depreciation & Amortisation | C16: =C7*Assumptions!$E$13 -> 1264.4439 | D16: =D7*Assumptions!$E$13 -> 1333.9883 | E16: =E7*Assumptions!$E$13 -> 1407.3576 | F16: =F7*Assumptions!$E$13 -> 1484.7623 | G16: =G7*Assumptions!$E$13 -> 1566.4242
B17: CapEx | C17: =C7*Assumptions!$E$14 -> 2023.1102 | D17: =D7*Assumptions!$E$14 -> 2134.3813 | E17: =E7*Assumptions!$E$14 -> 2251.7722 | F17: =F7*Assumptions!$E$14 -> 2375.6197 | G17: =G7*Assumptions!$E$14 -> 2506.2788
B18: Change in Net Working Capital | C18: =C7*Assumptions!$E$15 -> 505.77755 | D18: =D7*Assumptions!$E$15 -> 533.59532 | E18: =E7*Assumptions!$E$15 -> 562.94306 | F18: =F7*Assumptions!$E$15 -> 593.90493 | G18: =G7*Assumptions!$E$15 -> 626.5697
A21: x | B21: Output | C21: 2026 | D21: =C21+1 -> 2027 | E21: =D21+1 -> 2028 | F21: =E21+1 -> 2029 | G21: =F21+1 -> 2030
B22: Unlevered Free Cash Flow | C22: =C12+C16-C17-C18 -> 10224.293 | D22: =D12+D16-D17-D18 -> 10786.629 | E22: =E12+E16-E17-E18 -> 11379.894 | F22: =F12+F16-F17-F18 -> 12005.788 | G22: =G12+G16-G17-G18 -> 12666.106

Sheet WACC
B2: WACC
A5: x | B5: Cost of Equity (CAPM)
B6: Risk-Free Rate | C6: =Assumptions!E18 -> 0.04
B7: Beta | C7: =Assumptions!E20 -> 0.6
B8: Equity Risk Premium | C8: =Assumptions!E19 -> 0.055
B9: Cost of Equity | C9: =C6+C7*C8 -> 0.073
A12: x | B12: Cost of Debt
B13: Pre-tax Cost of Debt | C13: =Assumptions!E21 -> 0.045
B14: Tax Rate | C14: =Assumptions!E12 -> 0.23
B15: After-tax Cost of Debt | C15: =C13*(1-C14) -> 0.03465
A18: x | B18: Capital Structure
B19: Market Value of Equity | C19: =Assumptions!E23 -> 0.7
B20: Market Value of Debt | C20: =Assumptions!E22 -> 0.3
B21: Total Capital | C21: =C19+C20 -> 1
B22: Weight of Equity | C22: =C19/C21 -> 0.7
B23: Weight of Debt | C23: =C20/C21 -> 0.3
A26: x | B26: Final WACC | C26: =(C22*C9)+(C23*C15) -> 0.061495

Sheet Free Cash Flow
B2: Coca Cola - DCF
B4: (Figures in USD millions)
A5: x | B5: PV of Projected Cash Flows | C5: 2026 | D5: =C5+1 -> 2027 | E5: =D5+1 -> 2028 | F5: =E5+1 -> 2029 | G5: =F5+1 -> 2030
B6: Unlevered Free Cash Flow | C6: =Forecast!C22 -> 10224.293 | D6: =Forecast!D22 -> 10786.629 | E6: =Forecast!E22 -> 11379.894 | F6: =Forecast!F22 -> 12005.788 | G6: =Forecast!G22 -> 12666.106
B7: Discount Factor | C7: =1/(1+WACC!$C$26) -> 0.94206756 | D7: =C7/(1+WACC!$C$26) -> 0.88749128 | E7: =D7/(1+WACC!$C$26) -> 0.83607674 | F7: =E7/(1+WACC!$C$26) -> 0.78764077 | G7: =F7/(1+WACC!$C$26) -> 0.74201082
B8: Present Value of FCF | C8: =C6*C7 -> 9631.9749 | D8: =D6*D7 -> 9573.0394 | E8: =E6*E7 -> 9514.4646 | F8: =F6*F7 -> 9456.2482 | G8: =G6*G7 -> 9398.388
A11: x | B11: Terminal Value Section
B12: Terminal Growth Rate | C12: =Assumptions!E26 -> 0.0275
B13: Terminal Value | C13: =G6*(1+'Free Cash Flow'!C12)/(WACC!C26-'Free Cash Flow'!C12) -> 382833.49
B14: Present Value of Terminal Value | C14: =C13/(1+WACC!C26)^5 -> 284066.59
A17: x | B17: Valuation Summary
B18: Enterprise Value | C18: =SUM(C8:G8)+C14 -> 331640.7
B19: Less: Net Debt | C19: 30069
B20: Equity Value | C20: =C18-C19 -> 301571.7
B21: Shares Outstanding | C21: 7040
B22: Implied Share Price | C22: =C20/C21 -> 42.83689
B30: *Data from the Coca Cola 10K

Sheet DCF & Sensitivity
B2: Sensitivity Analysis
B5: Implied Share Price Sensitivity (WACC vs Terminal Growth)
D7: Terminal Growth Rate
B8: ='Free Cash Flow'!C22 -> 42.83689 | C8: 0.015 | D8: 0.02 | E8: 0.0275 | F8: 0.03 | G8: 0.035 | I8: Inputs
B9: 0.0515 | C9: =(NPV($B9,Forecast!$C$22:$G$22)+Forecast!$G$22*(1+C$8)/($B9-C$8)/(1+$B9)^5-'Free Cash Flow'!$C$19)/'Free Cash Flow'!$C$21 -> 41.603069 | D9: =(NPV($B9,Forecast!$C$22:$G$22)+Forecast!$G$22*(1+D$8)/($B9-D$8)/(1+$B9)^5-'Free Cash Flow'!$C$19)/'Free Cash Flow'!$C$21 -> 48.003364 | E9: =(NPV($B9,Forecast!$C$22:$G$22)+Forecast!$G$22*(1+E$8)/($B9-E$8)/(1+$B9)^5-'Free Cash Flow'!$C$19)/'Free Cash Flow'!$C$21 -> 62.604035 | F9: =(NPV($B9,Forecast!$C$22:$G$22)+Forecast!$G$22*(1+F$8)/($B9-F$8)/(1+$B9)^5-'Free Cash Flow'!$C$19)/'Free Cash Flow'!$C$21 -> 69.734596 | G9: =(NPV($B9,Forecast!$C$22:$G$22)+Forecast!$G$22*(1+G$8)/($B9-G$8)/(1+$B9)^5-'Free Cash Flow'!$C$19)/'Free Cash Flow'!$C$21 -> 90.478045 | I9: WACC | J9: =WACC!C26 -> 0.061495
B10: 0.0565 | C10: =(NPV($B10,Forecast!$C$22:$G$22)+Forecast!$G$22*(1+C$8)/($B10-C$8)/(1+$B10)^5-'Free Cash Flow'!$C$19)/'Free Cash Flow'!$C$21 -> 36.012929 | D10: =(NPV($B10,Forecast!$C$22:$G$22)+Forecast!$G$22*(1+D$8)/($B10-D$8)/(1+$B10)^5-'Free Cash Flow'!$C$19)/'Free Cash Flow'!$C$21 -> 40.77967 | E10: =(NPV($B10,Forecast!$C$22:$G$22)+Forecast!$G$22*(1+E$8)/($B10-E$8)/(1+$B10)^5-'Free Cash Flow'!$C$19)/'Free Cash Flow'!$C$21 -> 51.011725 | F10: =(NPV($B10,Forecast!$C$22:$G$22)+Forecast!$G$22*(1+F$8)/($B10-F$8)/(1+$B10)^5-'Free Cash Flow'!$C$19)/'Free Cash Flow'!$C$21 -> 55.709461 | G10: =(NPV($B10,Forecast!$C$22:$G$22)+Forecast!$G$22*(1+G$8)/($B10-G$8)/(1+$B10)^5-'Free Cash Flow'!$C$19)/'Free Cash Flow'!$C$21 -> 68.382423 | I10: Terminal Growth | J10: ='Free Cash Flow'!C12 -> 0.0275
B11: 0.0615 | C11: =(NPV($B11,Forecast!$C$22:$G$22)+Forecast!$G$22*(1+C$8)/($B11-C$8)/(1+$B11)^5-'Free Cash Flow'!$C$19)/'Free Cash Flow'!$C$21 -> 31.626026 | D11: =(NPV($B11,Forecast!$C$22:$G$22)+Forecast!$G$22*(1+D$8)/($B11-D$8)/(1+$B11)^5-'Free Cash Flow'!$C$19)/'Free Cash Flow'!$C$21 -> 35.29766 | E11: =(NPV($B11,Forecast!$C$22:$G$22)+Forecast!$G$22*(1+E$8)/($B11-E$8)/(1+$B11)^5-'Free Cash Flow'!$C$19)/'Free Cash Flow'!$C$21 -> 42.82991 | F11: =(NPV($B11,Forecast!$C$22:$G$22)+Forecast!$G$22*(1+F$8)/($B11-F$8)/(1+$B11)^5-'Free Cash Flow'!$C$19)/'Free Cash Flow'!$C$21 -> 46.137724 | G11: =(NPV($B11,Forecast!$C$22:$G$22)+Forecast!$G$22*(1+G$8)/($B11-G$8)/(1+$B11)^5-'Free Cash Flow'!$C$19)/'Free Cash Flow'!$C$21 -> 54.625698
B12: 0.0665 | C12: =(NPV($B12,Forecast!$C$22:$G$22)+Forecast!$G$22*(1+C$8)/($B12-C$8)/(1+$B12)^5-'Free Cash Flow'!$C$19)/'Free Cash Flow'!$C$21 -> 28.091879 | D12: =(NPV($B12,Forecast!$C$22:$G$22)+Forecast!$G$22*(1+D$8)/($B12-D$8)/(1+$B12)^5-'Free Cash Flow'!$C$19)/'Free Cash Flow'!$C$21 -> 30.995479 | E12: =(NPV($B12,Forecast!$C$22:$G$22)+Forecast!$G$22*(1+E$8)/($B12-E$8)/(1+$B12)^5-'Free Cash Flow'!$C$19)/'Free Cash Flow'!$C$21 -> 36.746842 | F12: =(NPV($B12,Forecast!$C$22:$G$22)+Forecast!$G$22*(1+F$8)/($B12-F$8)/(1+$B12)^5-'Free Cash Flow'!$C$19)/'Free Cash Flow'!$C$21 -> 39.189201 | G12: =(NPV($B12,Forecast!$C$22:$G$22)+Forecast!$G$22*(1+G$8)/($B12-G$8)/(1+$B12)^5-'Free Cash Flow'!$C$19)/'Free Cash Flow'!$C$21 -> 45.236948
B13: 0.0715 | C13: =(NPV($B13,Forecast!$C$22:$G$22)+Forecast!$G$22*(1+C$8)/($B13-C$8)/(1+$B13)^5-'Free Cash Flow'!$C$19)/'Free Cash Flow'!$C$21 -> 25.184072 | D13: =(NPV($B13,Forecast!$C$22:$G$22)+Forecast!$G$22*(1+D$8)/($B13-D$8)/(1+$B13)^5-'Free Cash Flow'!$C$19)/'Free Cash Flow'!$C$21 -> 27.529467 | E13: =(NPV($B13,Forecast!$C$22:$G$22)+Forecast!$G$22*(1+E$8)/($B13-E$8)/(1+$B13)^5-'Free Cash Flow'!$C$19)/'Free Cash Flow'!$C$21 -> 32.047019 | F13: =(NPV($B13,Forecast!$C$22:$G$22)+Forecast!$G$22*(1+F$8)/($B13-F$8)/(1+$B13)^5-'Free Cash Flow'!$C$19)/'Free Cash Flow'!$C$21 -> 33.915725 | G13: =(NPV($B13,Forecast!$C$22:$G$22)+Forecast!$G$22*(1+G$8)/($B13-G$8)/(1+$B13)^5-'Free Cash Flow'!$C$19)/'Free Cash Flow'!$C$21 -> 38.421099
