Workbook

Sheet Cover
M10: Discounted Cash Flow Valuation
M11: The Coca-Cola Company
M12: 5-Year Forecast Model
M15: Simon Norrman
M16: 22 Febraury 2026
M19: This model estimates the intrinsic value of The Coca-Cola Company using a 5-year DCF approach based on publicly available financial data
A34: *This model was built for educational purposes only and does not constitute investment advice

Sheet Assumptions
B2: Coca Cola DCF - Assumptions
A4: x | B4: Ticker | C4: KO
B5: Date | C5: 46076
A7: x | B7: Key Model Assumptions
A9: x | B9: Operating Assumptions
B10: Revenue Growth (Years 1-5) | E10: 0.04
B11: EBIT Margin | E11: 0.28
B12: Tax Rate | E12: 0.23
B13: Depreciation (% of Revenue) | E13: 0.05
B14: CapEx (% of Revenue) | E14: 0.06
B15: Change in NWC (% of Revenue) | E15: 0.01
A17: x | B17: WACC Assumptions
B18: Risk-Free Rate | E18: 4.0%
B19: Equity Risk Premium | E19: 5.5%
B20: Beta | E20: 0.6
B21: Cost of Debt | E21: 4.5%
B22: Target Debt % | E22: 0.3
B23: Target Equity % | E23: 0.7
A25: x | B25: Terminal Assumptions
B26: Terminal Growth Rate | E26: 2.5%

Sheet Historical Financials
B2: Historical Financials
B4: (Figures in USD millions)
A5: x | B5: Income Statement | C5: 2021 | D5: =C5+1 -> 2022 | E5: =D5+1 -> 2023 | F5: =E5+1 -> 2024 | G5: =F5+1 -> 2025
B6: Revenue | C6: 38655 | D6: 43004 | E6: 45754 | F6: 47061 | G6: 47941
B7: % Growth | C7: xx | D7: =(D6/C6)-1 -> 0.11250808 | E7: =(E6/D6)-1 -> 0.06394754 | F7: =(F6/E6)-1 -> 0.028565808 | G7: =(G6/F6)-1 -> 0.018699135
B8: EBIT (Operating Income) | C8: 10308 | D8: 10909 | E8: 11311 | F8: 9992 | G8: 13762
B9: EBIT Margin | C9: =C8/C6 -> 0.26666667 | D9: =D8/D6 -> 0.25367408 | E9: =E8/E6 -> 0.24721336 | F9: =F8/F6 -> 0.21232018 | G9: =G8/G6 -> 0.28706118
B10: Income Before Income Taxes | C10: 12425 | D10: 11686 | E10: 12925 | F10: 13086 | G10: 15998
B11: Income Tax Expense | C11: 2621 | D11: 2115 | E11: 2249 | F11: 2437 | G11: 2861
B12: Effective Tax Rate | C12: =C11/C10 -> 0.21094567 | D12: =D11/D10 -> 0.18098579 | E12: =E11/E10 -> 0.17400387 | F12: =F11/F10 -> 0.18622956 | G12: =G11/G10 -> 0.17883485
B13: Net Income | C13: 9771 | D13: 9542 | E13: 10714 | F13: 10631 | G13: 13107
A16: x | B16: Cash Flow Items | C16: 2021 | D16: =C16+1 -> 2022 | E16: =D16+1 -> 2023 | F16: =E16+1 -> 2024 | G16: =F16+1 -> 2025
B17: Depreciation & Amorisation | C17: 1425 | D17: 1260 | E17: 1128 | F17: 1075 | G17: 1050
B18: CapEx | C18: 1367 | D18: 1484 | E18: 1852 | F18: 2064 | G18: 2112
B19: Change in Net Working Capital | C19: 1325 | D19: -605 | E19: -846 | F19: -6234 | G19: -7208
A22: x | B22: Free Cash Flow (Historical) | C22: 2021 | D22: =C22+1 -> 2022 | E22: =D22+1 -> 2023 | F22: =E22+1 -> 2024 | G22: =F22+1 -> 2025
B23: NOPAT | C23: 8134 | D23: 8935 | E23: 9343 | F23: 8131 | G23: 11301
B24: Free Cash Flow | C24: =C23+C17-C18-C19 -> 6867 | D24: =D23+D17-D18-D19 -> 9316 | E24: =E23+E17-E18-E19 -> 9465 | F24: =F23+F17-F18-F19 -> 13376 | G24: =G23+G17-G18-G19 -> 17447
B33: *Historical revenue growth averaged 5,5% from 2021-2025; therefore the assumption of 4% makes sense
B34: *I will treat CapEx as a postive reinvestment amount in this model, and then subtract it later in the FCF

Sheet Forecast
B3: Forecast Financials (2026-2030)
B5: (Figures in USD millions)
A6: x | B6: Operating Forecast | C6: 2026 | D6: =C6+1 -> 2027 | E6: =D6+1 -> 2028 | F6: =E6+1 -> 2029 | G6: =F6+1 -> 2030
B7: Revenue | C7: ='Historical Financials'!G6*(1+Assumptions!$E$10) -> 49858.64 | D7: =C7*(1+Assumptions!$E$10) -> 51852.986 | E7: =D7*(1+Assumptions!$E$10) -> 53927.105 | F7: =E7*(1+Assumptions!$E$10) -> 56084.189 | G7: =F7*(1+Assumptions!$E$10) -> 58327.557
B8: % Growth | C8: =Assumptions!$E$10 -> 0.04 | D8: =Assumptions!$E$10 -> 0.04 | E8: =Assumptions!$E$10 -> 0.04 | F8: =Assumptions!$E$10 -> 0.04 | G8: =Assumptions!$E$10 -> 0.04
B9: EBIT Margin | C9: =Assumptions!$E$11 -> 0.28 | D9: =Assumptions!$E$11 -> 0.28 | E9: =Assumptions!$E$11 -> 0.28 | F9: =Assumptions!$E$11 -> 0.28 | G9: =Assumptions!$E$11 -> 0.28
B10: EBIT | C10: =C7*C9 -> 13960.419 | D10: =D7*D9 -> 14518.836 | E10: =E7*E9 -> 15099.589 | F10: =F7*F9 -> 15703.573 | G10: =G7*G9 -> 16331.716
B11: Tax Rate | C11: =Assumptions!$E$12 -> 0.23 | D11: =Assumptions!$E$12 -> 0.23 | E11: =Assumptions!$E$12 -> 0.23 | F11: =Assumptions!$E$12 -> 0.23 | G11: =Assumptions!$E$12 -> 0.23
B12: NOPAT | C12: =C10*(1-C11) -> 10749.523 | D12: =D10*(1-D11) -> 11179.504 | E12: =E10*(1-E11) -> 11626.684 | F12: =F10*(1-F11) -> 12091.751 | G12: =G10*(1-G11) -> 12575.421
A15: x | B15: Reinvestment | C15: 2026 | D15: =C15+1 -> 2027 | E15: =D15+1 -> 2028 | F15: =E15+1 -> 2029 | G15: =F15+1 -> 2030
B16: Depreciation & Amortisation | C16: =C7*Assumptions!$E$13 -> 2492.932 | D16: =D7*Assumptions!$E$13 -> 2592.6493 | E16: =E7*Assumptions!$E$13 -> 2696.3553 | F16: =F7*Assumptions!$E$13 -> 2804.2095 | G16: =G7*Assumptions!$E$13 -> 2916.3778
B17: CapEx | C17: =C7*Assumptions!$E$14 -> 2991.5184 | D17: =D7*Assumptions!$E$14 -> 3111.1791 | E17: =E7*Assumptions!$E$14 -> 3235.6263 | F17: =F7*Assumptions!$E$14 -> 3365.0514 | G17: =G7*Assumptions!$E$14 -> 3499.6534
B18: Change in Net Working Capital | C18: =C7*Assumptions!$E$15 -> 498.5864 | D18: =D7*Assumptions!$E$15 -> 518.52986 | E18: =E7*Assumptions!$E$15 -> 539.27105 | F18: =F7*Assumptions!$E$15 -> 560.84189 | G18: =G7*Assumptions!$E$15 -> 583.27557
A21: x | B21: Output | C21: 2026 | D21: =C21+1 -> 2027 | E21: =D21+1 -> 2028 | F21: =E21+1 -> 2029 | G21: =F21+1 -> 2030
B22: Free Cash Flow | C22: =C12+C16-C17-C18 -> 9752.35 | D22: =D12+D16-D17-D18 -> 10142.444 | E22: =E12+E16-E17-E18 -> 10548.142 | F22: =F12+F16-F17-F18 -> 10970.067 | G22: =G12+G16-G17-G18 -> 11408.87

Sheet WACC
B2: WACC
A5: x | B5: Cost of Equity (CAPM)
B6: Risk-Free Rate | C6: 0.043
B7: Beta | C7: 0.6
B8: Equity Risk Premium | C8: 0.055
B9: Cost of Equity | C9: =C6+C7*C8 -> 0.076
A12: x | B12: Cost of Debt
B13: Pre-tax Cost of Debt | C13: 0.05
B14: Tax Rate | C14: 0.23
B15: After-tax Cost of Debt | C15: =C13*(1-C14) -> 0.0385
A18: x | B18: Capital Structure
B19: Market Value of Equity | C19: 0.8
B20: Market Value of Debt | C20: 0.2
B21: Total Capital | C21: =C19+C20 -> 1
B22: Weight of Equity | C22: =C19/C21 -> 0.8
B23: Weight of Debt | C23: =C20/C21 -> 0.2
A26: x | B26: Final WACC | C26: =(C22*C9)+(C23*C15)*(1-C14) -> 0.066729

Sheet Free Cash Flow
B2: Coca Cola - DCF
B4: (Figures in USD millions)
A5: x | B5: PV of Projected Cash Flows | C5: 2026 | D5: =C5+1 -> 2027 | E5: =D5+1 -> 2028 | F5: =E5+1 -> 2029 | G5: =F5+1 -> 2030
B6: Free Cash Flow | C6: =Forecast!C22 -> 9752.35 | D6: =Forecast!D22 -> 10142.444 | E6: =Forecast!E22 -> 10548.142 | F6: =Forecast!F22 -> 10970.067 | G6: =Forecast!G22 -> 11408.87
B7: Discount Factor | C7: =1/(1+WACC!$C$26) -> 0.93744522 | D7: =C7/(1+WACC!$C$26) -> 0.87880354 | E7: =D7/(1+WACC!$C$26) -> 0.82383017 | F7: =E7/(1+WACC!$C$26) -> 0.77229566 | G7: =F7/(1+WACC!$C$26) -> 0.72398487
B8: Present Value of FCF | C8: =C6*C7 -> 9142.2939 | D8: =D6*D7 -> 8913.2156 | E8: =E6*E7 -> 8689.8774 | F8: =F6*F7 -> 8472.1354 | G8: =G6*G7 -> 8259.8493
A11: x | B11: Terminal Value Section
B12: Terminal Growth Rate | C12: 0.025
B13: Terminal Value | C13: =G6*(1+'DCF & Sensitivity'!$J$10)/('DCF & Sensitivity'!$J$9-'DCF & Sensitivity'!$J$10) -> 280238.97
B14: Present Value of Terminal Value | C14: =C13/(1+WACC!C26)^5 -> 202888.77
A17: x | B17: Valuation Summary
B18: Enterprise Value | C18: =SUM(C8:G8)+C14 -> 246366.14
B19: Less: Net Debt | C19: 30069
B20: Equity Value | C20: =C18-C19 -> 216297.14
B21: Shares Outstanding | C21: 7040
B22: Implied Share Price | C22: =C20/C21 -> 30.724026
B30: *Data from the Coca Cola 10K
B31: Formula to find total debt = Current maturities of long term debt + Long-term debt
B32: Total Debt = 1,822 + 42,119 = 43,941
B33: Then to find Net Debt = Total Debt - Cash (Total Cash, Cahs Equivalents and Short-Term Investments)
B34: Net Debt = 43,941-13,872=30,069

Sheet DCF & Sensitivity
B2: Sensitivity
B5: Implied Share Price Sensitivity (WACC vs Terminal Growth)
D7: Terminal Growth Rate
B8: ='Free Cash Flow'!C22 -> 30.724026 | C8: 0.015 | D8: 0.02 | E8: 0.025 | F8: 0.03 | G8: 0.035 | I8: Inputs
B9: 0.06 | C9: 28.368446 | D9: 31.823087 | E9: 36.264767 | F9: 42.187007 | G9: 50.478144 | I9: WACC | J9: =WACC!C26 -> 0.066729
B10: 0.065 | C10: 25.722062 | D10: 28.49881 | E10: 31.969746 | F10: 36.432378 | G10: 42.382553 | I10: Terminal Growth | J10: ='Free Cash Flow'!C12 -> 0.025
B11: 0.0667 | C11: 24.938895 | D11: 27.530713 | E11: 30.744068 | F11: 34.832998 | G11: 40.211811
B12: 0.075 | C12: 21.752484 | D12: 23.663499 | E12: 25.956716 | F12: 28.759538 | G12: 32.263064
B13: 0.08 | C13: 20.225724 | D13: 21.850257 | E13: 23.77016 | F13: 26.074044 | G13: 28.889902
